{
  "ApplicationMatch": "108362.1.6541",
  "applicationType": 1,
  "rows": [
    {
      "columns": [
        {
          "type": "column",
          "span": 12,
          "guid": "901416f9-1a58-0c0c-e0f7-48e472188bd1",
          "isRoot": true,
          "heightType": "auto",
          "borderless": false,
          "headerless": false,
          "isSmallerThanAddComponent": false,
          "mergeble": {},
          "component": {
            "applicationID": "108365.1.6541",
            "status": "1",
            "name": "InosaUserManagement",
            "applicationMatch": "InosaUserManagement",
            "checksum": "f8c3028c522ee4c25ad68394ea3d9918ba847d63",
            "description": "",
            "isLazy": false,
            "id": "108365.1.6541"
          },
          "selected": true,
          "borderRight": true,
          "borderLeft": true,
          "borderTop": true,
          "borderBottom": true,
          "background": true,
          "growHeight": false
        }
      ],
      "guid": "50d24602-fdda-7987-30af-8ffecc3fdb13"
    }
  ],
  "parameterMap": {
    "componentList": {
      "901416f9-1a58-0c0c-e0f7-48e472188bd1": {
        "applicationID": "108365.1.6541",
        "status": "1",
        "name": "InosaUserManagement",
        "applicationMatch": "InosaUserManagement",
        "checksum": "f8c3028c522ee4c25ad68394ea3d9918ba847d63",
        "description": "",
        "isLazy": true,
        "parameternames": [
          {
            "parameterName": "userId",
            "parameterDescription": "Newly created user identifier",
            "parameterValue": "parameter1"
          }
        ],
        "id": "108365.1.6541"
      }
    },
    "parameterUrl": "parameter1/parameter2",
    "popupParameters": {},
    "paramKeys": [ "parameter1", "parameter2" ]
  },
  "parameterUrl": "parameter1/parameter2",
  "lookupComponents": [ { "componentName": "InosaDataServiceRbClass" } ],
  "numberOfInitiallyLoadedComponents": 1,
  "rbappEditor": true,
  "checkSum": "7f6b506807c380aaa49ee8db548ad384485587de",
  "name": "UserManagement",
  "serverFolderName": "108362.1.6541"
}
